csv_remapper_lib/__init__.py
csv_remapper_lib/csv_remapper.py
csv_remapper_lib-1.2.2.dist-info/LICENSE
csv_remapper_lib-1.2.2.dist-info/METADATA
csv_remapper_lib-1.2.2.dist-info/WHEEL
csv_remapper_lib-1.2.2.dist-info/RECORD
