Metadata-Version: 2.3
Name: csv_remapper_lib
Version: 1.2.2
Summary: A library for remapping CSV files based on a mapping file.
License: AGPL v3
Keywords: csv,remap,data
Author: Víctor Carrasco
Author-email: vc.business.oo@gmail.com
Requires-Python: >=3.12
Classifier: License :: OSI Approved :: GNU Affero General Public License v3
Classifier: License :: Other/Proprietary License
Classifier: Operating System :: OS Independent
Classifier: Programming Language :: Python :: 3
Classifier: Programming Language :: Python :: 3.12
Classifier: Programming Language :: Python :: 3.13
Requires-Dist: python-dateutil (>=2.9.0.post0,<3.0.0)
Project-URL: Homepage, https://github.com/MyNameIsClown/csv_remapper_lib
Project-URL: Repository, https://github.com/MyNameIsClown/csv_remapper_lib
